<?xml version="1.0" encoding="UTF-8" standalone="no"?><feature-model xmlns:xsi="http://www.w3.org/2001/XMLSchema-instance" xsi:noNamespaceSchemaLocation="http://www.tdg-seville.info/benavides/featuremodelling/feature-model.xsd"><feature name="root"><binaryRelation name="R-1"><cardinality max="1" min="1"/><solitaryFeature name="F1"><binaryRelation name="R-7"><cardinality max="1" min="1"/><solitaryFeature name="F7"/></binaryRelation><binaryRelation name="R-8"><cardinality max="1" min="0"/><solitaryFeature name="F8"/></binaryRelation><binaryRelation name="R-9"><cardinality max="1" min="1"/><solitaryFeature name="F9"><binaryRelation name="R-24"><cardinality max="1" min="0"/><solitaryFeature name="F30"/></binaryRelation><binaryRelation name="R-25"><cardinality max="1" min="1"/><solitaryFeature name="F31"/></binaryRelation><binaryRelation name="R-26"><cardinality max="1" min="1"/><solitaryFeature name="F32"/></binaryRelation><binaryRelation name="R-27"><cardinality max="1" min="0"/><solitaryFeature name="F33"/></binaryRelation><setRelation name="R-28"><cardinality max="2" min="1"/><groupedFeature name="F34"><binaryRelation name="R-54"><cardinality max="1" min="1"/><solitaryFeature name="F69"/></binaryRelation></groupedFeature><groupedFeature name="F35"/></setRelation><setRelation name="R-29"><cardinality max="2" min="1"/><groupedFeature name="F36"/><groupedFeature name="F37"/></setRelation><setRelation name="R-30"><cardinality max="1" min="1"/><groupedFeature name="F38"/><groupedFeature name="F39"/></setRelation></solitaryFeature></binaryRelation><setRelation name="R-10"><cardinality max="2" min="1"/><groupedFeature name="F10"/><groupedFeature name="F11"><binaryRelation name="R-51"><cardinality max="1" min="1"/><solitaryFeature name="F65"/></binaryRelation><binaryRelation name="R-52"><cardinality max="1" min="0"/><solitaryFeature name="F66"/></binaryRelation><setRelation name="R-53"><cardinality max="1" min="1"/><groupedFeature name="F67"/><groupedFeature name="F68"/></setRelation></groupedFeature></setRelation><setRelation name="R-11"><cardinality max="3" min="1"/><groupedFeature name="F12"/><groupedFeature name="F13"><binaryRelation name="R-13"><cardinality max="1" min="1"/><solitaryFeature name="F17"/></binaryRelation></groupedFeature><groupedFeature name="F14"><binaryRelation name="R-14"><cardinality max="1" min="0"/><solitaryFeature name="F18"/></binaryRelation><binaryRelation name="R-15"><cardinality max="1" min="0"/><solitaryFeature name="F19"/></binaryRelation><setRelation name="R-16"><cardinality max="1" min="1"/><groupedFeature name="F20"><binaryRelation name="R-31"><cardinality max="1" min="0"/><solitaryFeature name="F40"/></binaryRelation><binaryRelation name="R-32"><cardinality max="1" min="1"/><solitaryFeature name="F41"/></binaryRelation><binaryRelation name="R-33"><cardinality max="1" min="0"/><solitaryFeature name="F42"><binaryRelation name="R-46"><cardinality max="1" min="0"/><solitaryFeature name="F58"/></binaryRelation><binaryRelation name="R-47"><cardinality max="1" min="0"/><solitaryFeature name="F59"/></binaryRelation><binaryRelation name="R-48"><cardinality max="1" min="0"/><solitaryFeature name="F60"/></binaryRelation><setRelation name="R-49"><cardinality max="1" min="1"/><groupedFeature name="F61"/><groupedFeature name="F62"/></setRelation><setRelation name="R-50"><cardinality max="1" min="1"/><groupedFeature name="F63"/><groupedFeature name="F64"/></setRelation></solitaryFeature></binaryRelation><binaryRelation name="R-34"><cardinality max="1" min="0"/><solitaryFeature name="F43"/></binaryRelation></groupedFeature><groupedFeature name="F21"><binaryRelation name="R-17"><cardinality max="1" min="0"/><solitaryFeature name="F22"/></binaryRelation><binaryRelation name="R-18"><cardinality max="1" min="0"/><solitaryFeature name="F23"><binaryRelation name="R-43"><cardinality max="1" min="0"/><solitaryFeature name="F55"/></binaryRelation><binaryRelation name="R-44"><cardinality max="1" min="0"/><solitaryFeature name="F56"/></binaryRelation><binaryRelation name="R-45"><cardinality max="1" min="1"/><solitaryFeature name="F57"/></binaryRelation></solitaryFeature></binaryRelation><binaryRelation name="R-19"><cardinality max="1" min="0"/><solitaryFeature name="F24"/></binaryRelation><binaryRelation name="R-20"><cardinality max="1" min="0"/><solitaryFeature name="F25"/></binaryRelation><binaryRelation name="R-21"><cardinality max="1" min="0"/><solitaryFeature name="F26"/></binaryRelation><binaryRelation name="R-22"><cardinality max="1" min="0"/><solitaryFeature name="F27"/></binaryRelation><setRelation name="R-23"><cardinality max="1" min="1"/><groupedFeature name="F28"/><groupedFeature name="F29"><binaryRelation name="R-42"><cardinality max="1" min="0"/><solitaryFeature name="F54"/></binaryRelation></groupedFeature></setRelation></groupedFeature></setRelation></groupedFeature></setRelation><setRelation name="R-12"><cardinality max="1" min="1"/><groupedFeature name="F15"/><groupedFeature name="F16"/></setRelation></solitaryFeature></binaryRelation><binaryRelation name="R-2"><cardinality max="1" min="1"/><solitaryFeature name="F2"/></binaryRelation><binaryRelation name="R-3"><cardinality max="1" min="0"/><solitaryFeature name="F3"/></binaryRelation><binaryRelation name="R-4"><cardinality max="1" min="1"/><solitaryFeature name="F4"><binaryRelation name="R-36"><cardinality max="1" min="0"/><solitaryFeature name="F45"/></binaryRelation><binaryRelation name="R-37"><cardinality max="1" min="1"/><solitaryFeature name="F46"/></binaryRelation><binaryRelation name="R-38"><cardinality max="1" min="1"/><solitaryFeature name="F47"/></binaryRelation><setRelation name="R-39"><cardinality max="2" min="1"/><groupedFeature name="F48"/><groupedFeature name="F49"/></setRelation><setRelation name="R-40"><cardinality max="1" min="1"/><groupedFeature name="F50"/><groupedFeature name="F51"/></setRelation><setRelation name="R-41"><cardinality max="1" min="1"/><groupedFeature name="F52"/><groupedFeature name="F53"/></setRelation></solitaryFeature></binaryRelation><binaryRelation name="R-5"><cardinality max="1" min="0"/><solitaryFeature name="F5"/></binaryRelation><binaryRelation name="R-6"><cardinality max="1" min="0"/><solitaryFeature name="F6"><binaryRelation name="R-35"><cardinality max="1" min="1"/><solitaryFeature name="F44"/></binaryRelation></solitaryFeature></binaryRelation></feature><excludes excludes="F3" feature="F47" name="R-55"/><excludes excludes="F19" feature="F26" name="R-56"/><requires feature="F60" name="R-57" requires="F50"/><requires feature="F28" name="R-58" requires="F22"/><requires feature="F30" name="R-59" requires="F40"/><excludes excludes="F11" feature="F18" name="R-60"/><requires feature="F46" name="R-61" requires="F31"/><requires feature="F53" name="R-62" requires="F64"/><requires feature="F54" name="R-63" requires="F5"/><excludes excludes="F58" feature="F27" name="R-64"/><requires feature="F29" name="R-65" requires="F6"/><excludes excludes="F22" feature="F49" name="R-66"/><excludes excludes="F58" feature="F52" name="R-67"/><requires feature="F25" name="R-68" requires="F2"/><excludes excludes="F56" feature="F49" name="R-69"/><excludes excludes="F35" feature="F62" name="R-70"/><excludes excludes="F52" feature="F36" name="R-71"/><excludes excludes="F66" feature="F60" name="R-72"/><excludes excludes="F64" feature="F23" name="R-73"/><requires feature="F6" name="R-74" requires="F37"/><requires feature="F10" name="R-75" requires="F43"/></feature-model>