<?xml version="1.0" encoding="UTF-8" standalone="no"?><feature-model xmlns:xsi="http://www.w3.org/2001/XMLSchema-instance" xsi:noNamespaceSchemaLocation="http://www.tdg-seville.info/benavides/featuremodelling/feature-model.xsd"><feature name="root"><binaryRelation name="R-1"><cardinality max="1" min="1"/><solitaryFeature name="F1"><binaryRelation name="R-2"><cardinality max="1" min="0"/><solitaryFeature name="F2"><binaryRelation name="R-3"><cardinality max="1" min="1"/><solitaryFeature name="F3"><setRelation name="R-91"><cardinality max="1" min="1"/><groupedFeature name="F129"/><groupedFeature name="F130"/></setRelation></solitaryFeature></binaryRelation><binaryRelation name="R-4"><cardinality max="1" min="1"/><solitaryFeature name="F4"><binaryRelation name="R-12"><cardinality max="1" min="1"/><solitaryFeature name="F16"/></binaryRelation><binaryRelation name="R-13"><cardinality max="1" min="1"/><solitaryFeature name="F17"><binaryRelation name="R-25"><cardinality max="1" min="0"/><solitaryFeature name="F33"><binaryRelation name="R-141"><cardinality max="1" min="1"/><solitaryFeature name="F197"/></binaryRelation><binaryRelation name="R-142"><cardinality max="1" min="1"/><solitaryFeature name="F198"/></binaryRelation></solitaryFeature></binaryRelation><binaryRelation name="R-26"><cardinality max="1" min="1"/><solitaryFeature name="F34"><binaryRelation name="R-93"><cardinality max="1" min="1"/><solitaryFeature name="F132"><binaryRelation name="R-116"><cardinality max="1" min="0"/><solitaryFeature name="F164"/></binaryRelation><binaryRelation name="R-117"><cardinality max="1" min="1"/><solitaryFeature name="F165"/></binaryRelation></solitaryFeature></binaryRelation><binaryRelation name="R-94"><cardinality max="1" min="0"/><solitaryFeature name="F133"/></binaryRelation><binaryRelation name="R-95"><cardinality max="1" min="1"/><solitaryFeature name="F134"/></binaryRelation><binaryRelation name="R-96"><cardinality max="1" min="1"/><solitaryFeature name="F135"/></binaryRelation><binaryRelation name="R-97"><cardinality max="1" min="1"/><solitaryFeature name="F136"/></binaryRelation><setRelation name="R-98"><cardinality max="1" min="1"/><groupedFeature name="F137"/><groupedFeature name="F138"/></setRelation></solitaryFeature></binaryRelation><setRelation name="R-27"><cardinality max="3" min="1"/><groupedFeature name="F35"><binaryRelation name="R-30"><cardinality max="1" min="0"/><solitaryFeature name="F42"><binaryRelation name="R-105"><cardinality max="1" min="0"/><solitaryFeature name="F147"/></binaryRelation><binaryRelation name="R-106"><cardinality max="1" min="0"/><solitaryFeature name="F148"/></binaryRelation><binaryRelation name="R-107"><cardinality max="1" min="0"/><solitaryFeature name="F149"/></binaryRelation><binaryRelation name="R-108"><cardinality max="1" min="0"/><solitaryFeature name="F150"><binaryRelation name="R-118"><cardinality max="1" min="1"/><solitaryFeature name="F166"/></binaryRelation><binaryRelation name="R-119"><cardinality max="1" min="0"/><solitaryFeature name="F167"/></binaryRelation><binaryRelation name="R-120"><cardinality max="1" min="0"/><solitaryFeature name="F168"/></binaryRelation><setRelation name="R-121"><cardinality max="2" min="1"/><groupedFeature name="F169"/><groupedFeature name="F170"/></setRelation><setRelation name="R-122"><cardinality max="1" min="1"/><groupedFeature name="F171"/><groupedFeature name="F172"/><groupedFeature name="F173"/></setRelation></solitaryFeature></binaryRelation><binaryRelation name="R-109"><cardinality max="1" min="1"/><solitaryFeature name="F151"/></binaryRelation><setRelation name="R-110"><cardinality max="2" min="1"/><groupedFeature name="F152"/><groupedFeature name="F153"/></setRelation><setRelation name="R-111"><cardinality max="2" min="1"/><groupedFeature name="F154"/><groupedFeature name="F155"/></setRelation></solitaryFeature></binaryRelation><setRelation name="R-31"><cardinality max="2" min="1"/><groupedFeature name="F43"/><groupedFeature name="F44"/></setRelation></groupedFeature><groupedFeature name="F36"/><groupedFeature name="F37"/></setRelation><setRelation name="R-28"><cardinality max="1" min="1"/><groupedFeature name="F38"/><groupedFeature name="F39"><binaryRelation name="R-29"><cardinality max="1" min="0"/><solitaryFeature name="F41"><binaryRelation name="R-41"><cardinality max="1" min="1"/><solitaryFeature name="F59"/></binaryRelation><binaryRelation name="R-42"><cardinality max="1" min="1"/><solitaryFeature name="F60"/></binaryRelation></solitaryFeature></binaryRelation></groupedFeature><groupedFeature name="F40"><setRelation name="R-69"><cardinality max="2" min="1"/><groupedFeature name="F97"><binaryRelation name="R-75"><cardinality max="1" min="1"/><solitaryFeature name="F109"/></binaryRelation><binaryRelation name="R-76"><cardinality max="1" min="0"/><solitaryFeature name="F110"><binaryRelation name="R-143"><cardinality max="1" min="1"/><solitaryFeature name="F199"/></binaryRelation></solitaryFeature></binaryRelation><setRelation name="R-77"><cardinality max="1" min="1"/><groupedFeature name="F111"/><groupedFeature name="F112"><binaryRelation name="R-80"><cardinality max="1" min="1"/><solitaryFeature name="F115"/></binaryRelation><binaryRelation name="R-81"><cardinality max="1" min="1"/><solitaryFeature name="F116"/></binaryRelation><binaryRelation name="R-82"><cardinality max="1" min="0"/><solitaryFeature name="F117"/></binaryRelation><binaryRelation name="R-83"><cardinality max="1" min="0"/><solitaryFeature name="F118"/></binaryRelation><binaryRelation name="R-84"><cardinality max="1" min="0"/><solitaryFeature name="F119"/></binaryRelation></groupedFeature></setRelation></groupedFeature><groupedFeature name="F98"/></setRelation></groupedFeature></setRelation></solitaryFeature></binaryRelation><binaryRelation name="R-14"><cardinality max="1" min="0"/><solitaryFeature name="F18"/></binaryRelation><binaryRelation name="R-15"><cardinality max="1" min="0"/><solitaryFeature name="F19"><binaryRelation name="R-32"><cardinality max="1" min="1"/><solitaryFeature name="F45"><binaryRelation name="R-52"><cardinality max="1" min="0"/><solitaryFeature name="F73"><binaryRelation name="R-58"><cardinality max="1" min="0"/><solitaryFeature name="F82"/></binaryRelation><binaryRelation name="R-59"><cardinality max="1" min="0"/><solitaryFeature name="F83"/></binaryRelation><binaryRelation name="R-60"><cardinality max="1" min="1"/><solitaryFeature name="F84"/></binaryRelation><binaryRelation name="R-61"><cardinality max="1" min="1"/><solitaryFeature name="F85"/></binaryRelation><binaryRelation name="R-62"><cardinality max="1" min="1"/><solitaryFeature name="F86"><binaryRelation name="R-85"><cardinality max="1" min="1"/><solitaryFeature name="F120"/></binaryRelation><binaryRelation name="R-86"><cardinality max="1" min="0"/><solitaryFeature name="F121"/></binaryRelation><binaryRelation name="R-87"><cardinality max="1" min="0"/><solitaryFeature name="F122"/></binaryRelation><binaryRelation name="R-88"><cardinality max="1" min="0"/><solitaryFeature name="F123"/></binaryRelation><setRelation name="R-89"><cardinality max="3" min="1"/><groupedFeature name="F124"/><groupedFeature name="F125"/><groupedFeature name="F126"><binaryRelation name="R-134"><cardinality max="1" min="0"/><solitaryFeature name="F188"/></binaryRelation><binaryRelation name="R-135"><cardinality max="1" min="1"/><solitaryFeature name="F189"/></binaryRelation><binaryRelation name="R-136"><cardinality max="1" min="1"/><solitaryFeature name="F190"/></binaryRelation><binaryRelation name="R-137"><cardinality max="1" min="0"/><solitaryFeature name="F191"/></binaryRelation><setRelation name="R-138"><cardinality max="2" min="1"/><groupedFeature name="F192"/><groupedFeature name="F193"/></setRelation><setRelation name="R-139"><cardinality max="1" min="1"/><groupedFeature name="F194"/><groupedFeature name="F195"/></setRelation></groupedFeature></setRelation><setRelation name="R-90"><cardinality max="1" min="1"/><groupedFeature name="F127"/><groupedFeature name="F128"/></setRelation></solitaryFeature></binaryRelation><binaryRelation name="R-63"><cardinality max="1" min="1"/><solitaryFeature name="F87"/></binaryRelation><setRelation name="R-64"><cardinality max="1" min="1"/><groupedFeature name="F88"/><groupedFeature name="F89"/></setRelation></solitaryFeature></binaryRelation><binaryRelation name="R-53"><cardinality max="1" min="1"/><solitaryFeature name="F74"><binaryRelation name="R-92"><cardinality max="1" min="1"/><solitaryFeature name="F131"/></binaryRelation></solitaryFeature></binaryRelation><binaryRelation name="R-54"><cardinality max="1" min="0"/><solitaryFeature name="F75"/></binaryRelation><binaryRelation name="R-55"><cardinality max="1" min="0"/><solitaryFeature name="F76"/></binaryRelation><setRelation name="R-56"><cardinality max="2" min="1"/><groupedFeature name="F77"/><groupedFeature name="F78"><binaryRelation name="R-78"><cardinality max="1" min="0"/><solitaryFeature name="F113"/></binaryRelation></groupedFeature></setRelation><setRelation name="R-57"><cardinality max="1" min="1"/><groupedFeature name="F79"><binaryRelation name="R-79"><cardinality max="1" min="1"/><solitaryFeature name="F114"/></binaryRelation></groupedFeature><groupedFeature name="F80"/><groupedFeature name="F81"/></setRelation></solitaryFeature></binaryRelation><binaryRelation name="R-33"><cardinality max="1" min="1"/><solitaryFeature name="F46"><binaryRelation name="R-45"><cardinality max="1" min="0"/><solitaryFeature name="F63"><binaryRelation name="R-112"><cardinality max="1" min="0"/><solitaryFeature name="F156"/></binaryRelation><binaryRelation name="R-113"><cardinality max="1" min="1"/><solitaryFeature name="F157"/></binaryRelation><setRelation name="R-114"><cardinality max="3" min="1"/><groupedFeature name="F158"><binaryRelation name="R-140"><cardinality max="1" min="1"/><solitaryFeature name="F196"/></binaryRelation></groupedFeature><groupedFeature name="F159"/><groupedFeature name="F160"/></setRelation><setRelation name="R-115"><cardinality max="1" min="1"/><groupedFeature name="F161"/><groupedFeature name="F162"/><groupedFeature name="F163"/></setRelation></solitaryFeature></binaryRelation><binaryRelation name="R-46"><cardinality max="1" min="0"/><solitaryFeature name="F64"/></binaryRelation><binaryRelation name="R-47"><cardinality max="1" min="0"/><solitaryFeature name="F65"/></binaryRelation><binaryRelation name="R-48"><cardinality max="1" min="1"/><solitaryFeature name="F66"/></binaryRelation><setRelation name="R-49"><cardinality max="2" min="1"/><groupedFeature name="F67"/><groupedFeature name="F68"/></setRelation><setRelation name="R-50"><cardinality max="1" min="1"/><groupedFeature name="F69"><binaryRelation name="R-51"><cardinality max="1" min="0"/><solitaryFeature name="F72"/></binaryRelation></groupedFeature><groupedFeature name="F70"/><groupedFeature name="F71"/></setRelation></solitaryFeature></binaryRelation><setRelation name="R-34"><cardinality max="3" min="1"/><groupedFeature name="F47"/><groupedFeature name="F48"/><groupedFeature name="F49"><binaryRelation name="R-43"><cardinality max="1" min="0"/><solitaryFeature name="F61"/></binaryRelation><binaryRelation name="R-44"><cardinality max="1" min="0"/><solitaryFeature name="F62"/></binaryRelation></groupedFeature></setRelation><setRelation name="R-35"><cardinality max="1" min="1"/><groupedFeature name="F50"/><groupedFeature name="F51"/></setRelation></solitaryFeature></binaryRelation><binaryRelation name="R-16"><cardinality max="1" min="1"/><solitaryFeature name="F20"/></binaryRelation><binaryRelation name="R-17"><cardinality max="1" min="1"/><solitaryFeature name="F21"/></binaryRelation><setRelation name="R-18"><cardinality max="1" min="1"/><groupedFeature name="F22"/><groupedFeature name="F23"/><groupedFeature name="F24"/></setRelation></solitaryFeature></binaryRelation><binaryRelation name="R-5"><cardinality max="1" min="0"/><solitaryFeature name="F5"><binaryRelation name="R-9"><cardinality max="1" min="0"/><solitaryFeature name="F13"><binaryRelation name="R-24"><cardinality max="1" min="1"/><solitaryFeature name="F32"/></binaryRelation></solitaryFeature></binaryRelation><binaryRelation name="R-10"><cardinality max="1" min="1"/><solitaryFeature name="F14"/></binaryRelation><binaryRelation name="R-11"><cardinality max="1" min="0"/><solitaryFeature name="F15"/></binaryRelation></solitaryFeature></binaryRelation><setRelation name="R-6"><cardinality max="3" min="1"/><groupedFeature name="F6"/><groupedFeature name="F7"><binaryRelation name="R-65"><cardinality max="1" min="0"/><solitaryFeature name="F90"/></binaryRelation><binaryRelation name="R-66"><cardinality max="1" min="0"/><solitaryFeature name="F91"><binaryRelation name="R-70"><cardinality max="1" min="1"/><solitaryFeature name="F99"/></binaryRelation><binaryRelation name="R-71"><cardinality max="1" min="1"/><solitaryFeature name="F100"/></binaryRelation><binaryRelation name="R-72"><cardinality max="1" min="0"/><solitaryFeature name="F101"><binaryRelation name="R-127"><cardinality max="1" min="1"/><solitaryFeature name="F178"/></binaryRelation><binaryRelation name="R-128"><cardinality max="1" min="1"/><solitaryFeature name="F179"/></binaryRelation><binaryRelation name="R-129"><cardinality max="1" min="0"/><solitaryFeature name="F180"/></binaryRelation><binaryRelation name="R-130"><cardinality max="1" min="0"/><solitaryFeature name="F181"/></binaryRelation><binaryRelation name="R-131"><cardinality max="1" min="0"/><solitaryFeature name="F182"/></binaryRelation><setRelation name="R-132"><cardinality max="2" min="1"/><groupedFeature name="F183"/><groupedFeature name="F184"/></setRelation><setRelation name="R-133"><cardinality max="1" min="1"/><groupedFeature name="F185"/><groupedFeature name="F186"/><groupedFeature name="F187"/></setRelation></solitaryFeature></binaryRelation><setRelation name="R-73"><cardinality max="3" min="1"/><groupedFeature name="F102"/><groupedFeature name="F103"/><groupedFeature name="F104"/></setRelation><setRelation name="R-74"><cardinality max="1" min="1"/><groupedFeature name="F105"/><groupedFeature name="F106"/><groupedFeature name="F107"/><groupedFeature name="F108"/></setRelation></solitaryFeature></binaryRelation><setRelation name="R-67"><cardinality max="3" min="1"/><groupedFeature name="F92"/><groupedFeature name="F93"/><groupedFeature name="F94"/></setRelation><setRelation name="R-68"><cardinality max="1" min="1"/><groupedFeature name="F95"/><groupedFeature name="F96"/></setRelation></groupedFeature><groupedFeature name="F8"/></setRelation><setRelation name="R-7"><cardinality max="1" min="1"/><groupedFeature name="F9"><binaryRelation name="R-19"><cardinality max="1" min="0"/><solitaryFeature name="F25"/></binaryRelation><binaryRelation name="R-20"><cardinality max="1" min="1"/><solitaryFeature name="F26"/></binaryRelation><binaryRelation name="R-21"><cardinality max="1" min="1"/><solitaryFeature name="F27"/></binaryRelation><setRelation name="R-22"><cardinality max="2" min="1"/><groupedFeature name="F28"/><groupedFeature name="F29"><binaryRelation name="R-38"><cardinality max="1" min="1"/><solitaryFeature name="F54"/></binaryRelation><binaryRelation name="R-39"><cardinality max="1" min="1"/><solitaryFeature name="F55"/></binaryRelation><setRelation name="R-40"><cardinality max="1" min="1"/><groupedFeature name="F56"/><groupedFeature name="F57"/><groupedFeature name="F58"/></setRelation></groupedFeature></setRelation><setRelation name="R-23"><cardinality max="2" min="1"/><groupedFeature name="F30"><binaryRelation name="R-36"><cardinality max="1" min="0"/><solitaryFeature name="F52"/></binaryRelation><binaryRelation name="R-37"><cardinality max="1" min="1"/><solitaryFeature name="F53"/></binaryRelation></groupedFeature><groupedFeature name="F31"><binaryRelation name="R-99"><cardinality max="1" min="0"/><solitaryFeature name="F139"/></binaryRelation><binaryRelation name="R-100"><cardinality max="1" min="1"/><solitaryFeature name="F140"/></binaryRelation><binaryRelation name="R-101"><cardinality max="1" min="1"/><solitaryFeature name="F141"/></binaryRelation><binaryRelation name="R-102"><cardinality max="1" min="1"/><solitaryFeature name="F142"/></binaryRelation><setRelation name="R-103"><cardinality max="2" min="1"/><groupedFeature name="F143"/><groupedFeature name="F144"/></setRelation><setRelation name="R-104"><cardinality max="1" min="1"/><groupedFeature name="F145"/><groupedFeature name="F146"><binaryRelation name="R-123"><cardinality max="1" min="1"/><solitaryFeature name="F174"/></binaryRelation><binaryRelation name="R-124"><cardinality max="1" min="1"/><solitaryFeature name="F175"/></binaryRelation><binaryRelation name="R-125"><cardinality max="1" min="1"/><solitaryFeature name="F176"/></binaryRelation><binaryRelation name="R-126"><cardinality max="1" min="1"/><solitaryFeature name="F177"/></binaryRelation></groupedFeature></setRelation></groupedFeature></setRelation></groupedFeature><groupedFeature name="F10"/></setRelation><setRelation name="R-8"><cardinality max="1" min="1"/><groupedFeature name="F11"/><groupedFeature name="F12"/></setRelation></solitaryFeature></binaryRelation></solitaryFeature></binaryRelation></feature><requires feature="F129" name="R-144" requires="F36"/><requires feature="F68" name="R-145" requires="F175"/><excludes excludes="F88" feature="F84" name="R-146"/><requires feature="F184" name="R-147" requires="F61"/><excludes excludes="F79" feature="F21" name="R-148"/><excludes excludes="F73" feature="F180" name="R-149"/><excludes excludes="F112" feature="F25" name="R-150"/><excludes excludes="F174" feature="F118" name="R-151"/><excludes excludes="F44" feature="F112" name="R-152"/><excludes excludes="F193" feature="F6" name="R-153"/><requires feature="F65" name="R-154" requires="F6"/><excludes excludes="F25" feature="F152" name="R-155"/><requires feature="F170" name="R-156" requires="F119"/><excludes excludes="F52" feature="F119" name="R-157"/><excludes excludes="F49" feature="F107" name="R-158"/><requires feature="F92" name="R-159" requires="F62"/><requires feature="F192" name="R-160" requires="F164"/><requires feature="F111" name="R-161" requires="F182"/><excludes excludes="F96" feature="F54" name="R-162"/><excludes excludes="F169" feature="F130" name="R-163"/><requires feature="F110" name="R-164" requires="F22"/><requires feature="F13" name="R-165" requires="F43"/><excludes excludes="F123" feature="F83" name="R-166"/><excludes excludes="F120" feature="F198" name="R-167"/><requires feature="F108" name="R-168" requires="F33"/><requires feature="F55" name="R-169" requires="F184"/><excludes excludes="F24" feature="F166" name="R-170"/><excludes excludes="F93" feature="F26" name="R-171"/><excludes excludes="F124" feature="F28" name="R-172"/><excludes excludes="F14" feature="F174" name="R-173"/><excludes excludes="F123" feature="F176" name="R-174"/><requires feature="F44" name="R-175" requires="F81"/><requires feature="F115" name="R-176" requires="F51"/><excludes excludes="F15" feature="F157" name="R-177"/><excludes excludes="F47" feature="F194" name="R-178"/><excludes excludes="F126" feature="F163" name="R-179"/><requires feature="F180" name="R-180" requires="F59"/><requires feature="F120" name="R-181" requires="F182"/><requires feature="F124" name="R-182" requires="F174"/><excludes excludes="F54" feature="F175" name="R-183"/><requires feature="F33" name="R-184" requires="F184"/><excludes excludes="F58" feature="F14" name="R-185"/><excludes excludes="F169" feature="F36" name="R-186"/><requires feature="F64" name="R-187" requires="F118"/><excludes excludes="F5" feature="F27" name="R-188"/><excludes excludes="F158" feature="F20" name="R-189"/><excludes excludes="F153" feature="F104" name="R-190"/><excludes excludes="F132" feature="F142" name="R-191"/><requires feature="F62" name="R-192" requires="F104"/><requires feature="F60" name="R-193" requires="F153"/><requires feature="F141" name="R-194" requires="F27"/><requires feature="F82" name="R-195" requires="F13"/><requires feature="F72" name="R-196" requires="F147"/><requires feature="F147" name="R-197" requires="F126"/><excludes excludes="F199" feature="F42" name="R-198"/><requires feature="F45" name="R-199" requires="F118"/><excludes excludes="F9" feature="F93" name="R-200"/><requires feature="F89" name="R-201" requires="F139"/><requires feature="F174" name="R-202" requires="F120"/><excludes excludes="F151" feature="F38" name="R-203"/><requires feature="F120" name="R-204" requires="F81"/><excludes excludes="F23" feature="F25" name="R-205"/><excludes excludes="F134" feature="F50" name="R-206"/><excludes excludes="F15" feature="F142" name="R-207"/><requires feature="F112" name="R-208" requires="F94"/><requires feature="F119" name="R-209" requires="F87"/><excludes excludes="F138" feature="F155" name="R-210"/><requires feature="F123" name="R-211" requires="F149"/><requires feature="F174" name="R-212" requires="F5"/><requires feature="F30" name="R-213" requires="F114"/><requires feature="F59" name="R-214" requires="F5"/><excludes excludes="F75" feature="F9" name="R-215"/><excludes excludes="F190" feature="F192" name="R-216"/><requires feature="F28" name="R-217" requires="F112"/><requires feature="F7" name="R-218" requires="F35"/><excludes excludes="F49" feature="F113" name="R-219"/><excludes excludes="F27" feature="F48" name="R-220"/><requires feature="F184" name="R-221" requires="F196"/><excludes excludes="F35" feature="F91" name="R-222"/><requires feature="F148" name="R-223" requires="F188"/><excludes excludes="F155" feature="F133" name="R-224"/><excludes excludes="F108" feature="F49" name="R-225"/><excludes excludes="F57" feature="F110" name="R-226"/><excludes excludes="F67" feature="F49" name="R-227"/><requires feature="F58" name="R-228" requires="F39"/><requires feature="F124" name="R-229" requires="F168"/><requires feature="F37" name="R-230" requires="F12"/><requires feature="F173" name="R-231" requires="F181"/><excludes excludes="F134" feature="F163" name="R-232"/><excludes excludes="F54" feature="F172" name="R-233"/><excludes excludes="F78" feature="F49" name="R-234"/><requires feature="F191" name="R-235" requires="F40"/><excludes excludes="F85" feature="F159" name="R-236"/><excludes excludes="F91" feature="F78" name="R-237"/><excludes excludes="F52" feature="F188" name="R-238"/><excludes excludes="F141" feature="F16" name="R-239"/><excludes excludes="F65" feature="F48" name="R-240"/><requires feature="F173" name="R-241" requires="F106"/><excludes excludes="F122" feature="F20" name="R-242"/><excludes excludes="F153" feature="F171" name="R-243"/></feature-model>